{
	"backtrace" : 1,
	"backtraceGraph" : 
	{
		"commands" : 
		[
			"add_custom_target"
		],
		"files" : 
		[
			"CMakeLists.txt"
		],
		"nodes" : 
		[
			{
				"file" : 0
			},
			{
				"command" : 0,
				"file" : 0,
				"line" : 589,
				"parent" : 0
			}
		]
	},
	"dependencies" : 
	[
		{
			"id" : "game-shared::@6890427a1f51a3e7e1df"
		},
		{
			"id" : "engine-shared::@6890427a1f51a3e7e1df"
		},
		{
			"id" : "Mmotee-Server::@6890427a1f51a3e7e1df"
		},
		{
			"id" : "mastersrv::@6890427a1f51a3e7e1df"
		},
		{
			"id" : "ZERO_CHECK::@6890427a1f51a3e7e1df"
		}
	],
	"id" : "everything::@6890427a1f51a3e7e1df",
	"name" : "everything",
	"paths" : 
	{
		"build" : ".",
		"source" : "."
	},
	"sourceGroups" : 
	[
		{
			"name" : "",
			"sourceIndexes" : 
			[
				0
			]
		},
		{
			"name" : "CMake Rules",
			"sourceIndexes" : 
			[
				1
			]
		}
	],
	"sources" : 
	[
		{
			"backtrace" : 1,
			"isGenerated" : true,
			"path" : "build/CMakeFiles/everything",
			"sourceGroupIndex" : 0
		},
		{
			"backtrace" : 0,
			"isGenerated" : true,
			"path" : "build/CMakeFiles/c31ef533c86c89d8c386529e29045e90/everything.rule",
			"sourceGroupIndex" : 1
		}
	],
	"type" : "UTILITY"
}
